searchailib/__init__.py
searchailib/__main__.py
searchailib/cli.py
searchailib-0.1.0.dist-info/METADATA
searchailib-0.1.0.dist-info/WHEEL
searchailib-0.1.0.dist-info/entry_points.txt
searchailib-0.1.0.dist-info/top_level.txt
searchailib-0.1.0.dist-info/RECORD
